console_log.py
console_log-0.2.10.dist-info/DESCRIPTION.rst
console_log-0.2.10.dist-info/METADATA
console_log-0.2.10.dist-info/RECORD
console_log-0.2.10.dist-info/WHEEL
console_log-0.2.10.dist-info/metadata.json
console_log-0.2.10.dist-info/top_level.txt
