Metadata-Version: 2.0
Name: console-log
Version: 0.2.10
Summary: Log to browser console
Home-page: https://github.com/betodealmeida/consolelog
Author: Beto Dealmeida
Author-email: beto@lyft.com
License: MIT License
Requires-Dist: gevent
Requires-Dist: gevent-websocket
Requires-Dist: werkzeug
Requires-Dist: wsgigzip
Provides-Extra: dev
Requires-Dist: nose; extra == 'dev'
Requires-Dist: pipreqs; extra == 'dev'
Requires-Dist: twine; extra == 'dev'
Provides-Extra: examples
Requires-Dist: flask; extra == 'examples'
